{
  "topic": "instruments",
  "generated_at": "2025-12-19T10:22:03.159857",
  "files": [
    {
      "path": "MPK_Mini3_Knob_Assignments.txt",
      "absolute_path": "/app/repo/MPK_Mini3_Knob_Assignments.txt",
      "categories": [
        {
          "category": "instruments",
          "score": 8.5
        },
        {
          "category": "production",
          "score": 5.5
        },
        {
          "category": "daw_integration",
          "score": 3.5
        },
        {
          "category": "ml_ai",
          "score": 2.5
        },
        {
          "category": "audio_processing",
          "score": 2.5
        },
        {
          "category": "theory",
          "score": 1.0
        }
      ],
      "pipelines": []
    },
    {
      "path": "synth.py",
      "absolute_path": "/app/repo/synth.py",
      "categories": [
        {
          "category": "instruments",
          "score": 7.0
        }
      ],
      "pipelines": []
    },
    {
      "path": "tsconfig.node.json",
      "absolute_path": "/app/repo/tsconfig.node.json",
      "categories": [
        {
          "category": "instruments",
          "score": 2.5
        },
        {
          "category": "daw_integration",
          "score": 1.0
        }
      ],
      "pipelines": []
    },
    {
      "path": "Groove and Rhythm Guide.md",
      "absolute_path": "/app/repo/Groove and Rhythm Guide.md",
      "categories": [
        {
          "category": "instruments",
          "score": 12.0
        },
        {
          "category": "theory",
          "score": 4.0
        },
        {
          "category": "daw_integration",
          "score": 3.5
        },
        {
          "category": "production",
          "score": 2.5
        },
        {
          "category": "ml_ai",
          "score": 2.5
        },
        {
          "category": "emotion",
          "score": 2.5
        },
        {
          "category": "tools",
          "score": 2.5
        }
      ],
      "pipelines": []
    },
    {
      "path": "MVP_COMPLETE.md",
      "absolute_path": "/app/repo/MVP_COMPLETE.md",
      "categories": [
        {
          "category": "instruments",
          "score": 7.0
        },
        {
          "category": "production",
          "score": 6.5
        },
        {
          "category": "audio_processing",
          "score": 5.5
        },
        {
          "category": "tools",
          "score": 4.0
        },
        {
          "category": "daw_integration",
          "score": 3.5
        },
        {
          "category": "composition",
          "score": 3.5
        },
        {
          "category": "ml_ai",
          "score": 2.5
        },
        {
          "category": "emotion",
          "score": 2.5
        },
        {
          "category": "theory",
          "score": 2.0
        }
      ],
      "pipelines": []
    },
    {
      "path": "Synth Humanization Guide.md",
      "absolute_path": "/app/repo/Synth Humanization Guide.md",
      "categories": [
        {
          "category": "instruments",
          "score": 14.0
        },
        {
          "category": "production",
          "score": 10.5
        },
        {
          "category": "tools",
          "score": 6.0
        },
        {
          "category": "daw_integration",
          "score": 5.5
        },
        {
          "category": "ml_ai",
          "score": 5.0
        },
        {
          "category": "theory",
          "score": 4.5
        },
        {
          "category": "audio_processing",
          "score": 3.5
        },
        {
          "category": "composition",
          "score": 1.0
        }
      ],
      "pipelines": []
    },
    {
      "path": "Hook Writing Guide.md",
      "absolute_path": "/app/repo/Hook Writing Guide.md",
      "categories": [
        {
          "category": "instruments",
          "score": 9.5
        },
        {
          "category": "composition",
          "score": 9.0
        },
        {
          "category": "theory",
          "score": 5.5
        },
        {
          "category": "emotion",
          "score": 5.0
        },
        {
          "category": "production",
          "score": 2.5
        },
        {
          "category": "ml_ai",
          "score": 2.5
        },
        {
          "category": "daw_integration",
          "score": 2.0
        },
        {
          "category": "audio_processing",
          "score": 1.0
        }
      ],
      "pipelines": []
    },
    {
      "path": "drum_analysis.py",
      "absolute_path": "/app/repo/drum_analysis.py",
      "categories": [
        {
          "category": "instruments",
          "score": 8.0
        },
        {
          "category": "theory",
          "score": 3.5
        },
        {
          "category": "ml_ai",
          "score": 2.5
        },
        {
          "category": "audio_processing",
          "score": 2.5
        },
        {
          "category": "tools",
          "score": 1.5
        },
        {
          "category": "daw_integration",
          "score": 1.0
        }
      ],
      "pipelines": []
    },
    {
      "path": "SAMPLE_LIBRARY_COMPLETE.md",
      "absolute_path": "/app/repo/SAMPLE_LIBRARY_COMPLETE.md",
      "categories": [
        {
          "category": "instruments",
          "score": 9.5
        },
        {
          "category": "production",
          "score": 7.0
        },
        {
          "category": "tools",
          "score": 6.0
        },
        {
          "category": "composition",
          "score": 4.5
        },
        {
          "category": "daw_integration",
          "score": 3.5
        },
        {
          "category": "ml_ai",
          "score": 2.5
        },
        {
          "category": "theory",
          "score": 1.0
        },
        {
          "category": "audio_processing",
          "score": 1.0
        }
      ],
      "pipelines": []
    },
    {
      "path": "auto_emotion_sampler.py",
      "absolute_path": "/app/repo/auto_emotion_sampler.py",
      "categories": [
        {
          "category": "instruments",
          "score": 8.5
        },
        {
          "category": "emotion",
          "score": 7.0
        },
        {
          "category": "daw_integration",
          "score": 5.5
        },
        {
          "category": "tools",
          "score": 4.0
        },
        {
          "category": "production",
          "score": 3.5
        },
        {
          "category": "ml_ai",
          "score": 2.5
        },
        {
          "category": "audio_processing",
          "score": 2.5
        },
        {
          "category": "theory",
          "score": 1.0
        },
        {
          "category": "composition",
          "score": 1.0
        }
      ],
      "pipelines": [
        "daw"
      ]
    },
    {
      "path": "Logic_Template_Setup_Guide.txt",
      "absolute_path": "/app/repo/Logic_Template_Setup_Guide.txt",
      "categories": [
        {
          "category": "instruments",
          "score": 9.5
        },
        {
          "category": "daw_integration",
          "score": 9.0
        },
        {
          "category": "theory",
          "score": 5.5
        },
        {
          "category": "production",
          "score": 4.5
        },
        {
          "category": "composition",
          "score": 3.5
        },
        {
          "category": "ml_ai",
          "score": 2.5
        },
        {
          "category": "audio_processing",
          "score": 1.0
        }
      ],
      "pipelines": []
    },
    {
      "path": "logic_pro.py",
      "absolute_path": "/app/repo/logic_pro.py",
      "categories": [
        {
          "category": "instruments",
          "score": 12.0
        },
        {
          "category": "daw_integration",
          "score": 9.0
        },
        {
          "category": "production",
          "score": 4.5
        },
        {
          "category": "theory",
          "score": 4.5
        },
        {
          "category": "composition",
          "score": 3.5
        },
        {
          "category": "tools",
          "score": 3.5
        },
        {
          "category": "ml_ai",
          "score": 2.5
        },
        {
          "category": "audio_processing",
          "score": 1.0
        }
      ],
      "pipelines": [
        "daw"
      ]
    },
    {
      "path": "instruments.py",
      "absolute_path": "/app/repo/instruments.py",
      "categories": [
        {
          "category": "instruments",
          "score": 15.0
        },
        {
          "category": "daw_integration",
          "score": 4.5
        },
        {
          "category": "production",
          "score": 4.0
        },
        {
          "category": "theory",
          "score": 2.5
        },
        {
          "category": "ml_ai",
          "score": 2.5
        },
        {
          "category": "audio_processing",
          "score": 1.0
        },
        {
          "category": "composition",
          "score": 1.0
        }
      ],
      "pipelines": []
    },
    {
      "path": "Bass Programming Guide.md",
      "absolute_path": "/app/repo/Bass Programming Guide.md",
      "categories": [
        {
          "category": "instruments",
          "score": 11.5
        },
        {
          "category": "production",
          "score": 7.0
        },
        {
          "category": "theory",
          "score": 4.5
        },
        {
          "category": "daw_integration",
          "score": 4.5
        },
        {
          "category": "audio_processing",
          "score": 3.5
        },
        {
          "category": "tools",
          "score": 3.5
        },
        {
          "category": "ml_ai",
          "score": 2.5
        }
      ],
      "pipelines": []
    },
    {
      "path": "orchestral.py",
      "absolute_path": "/app/repo/orchestral.py",
      "categories": [
        {
          "category": "instruments",
          "score": 8.0
        },
        {
          "category": "ml_ai",
          "score": 2.5
        },
        {
          "category": "theory",
          "score": 1.0
        },
        {
          "category": "daw_integration",
          "score": 1.0
        },
        {
          "category": "tools",
          "score": 1.0
        }
      ],
      "pipelines": []
    },
    {
      "path": "Dynamics and Arrangement Guide.md",
      "absolute_path": "/app/repo/Dynamics and Arrangement Guide.md",
      "categories": [
        {
          "category": "instruments",
          "score": 12.0
        },
        {
          "category": "composition",
          "score": 11.5
        },
        {
          "category": "theory",
          "score": 10.5
        },
        {
          "category": "production",
          "score": 9.5
        },
        {
          "category": "ml_ai",
          "score": 4.0
        },
        {
          "category": "audio_processing",
          "score": 3.5
        },
        {
          "category": "tools",
          "score": 3.5
        },
        {
          "category": "emotion",
          "score": 2.5
        },
        {
          "category": "daw_integration",
          "score": 1.0
        }
      ],
      "pipelines": []
    },
    {
      "path": "Guitar Programming Guide.md",
      "absolute_path": "/app/repo/Guitar Programming Guide.md",
      "categories": [
        {
          "category": "instruments",
          "score": 10.5
        },
        {
          "category": "theory",
          "score": 9.5
        },
        {
          "category": "production",
          "score": 8.5
        },
        {
          "category": "ml_ai",
          "score": 2.5
        },
        {
          "category": "daw_integration",
          "score": 2.5
        },
        {
          "category": "composition",
          "score": 2.0
        }
      ],
      "pipelines": []
    },
    {
      "path": "Sample Pack Review Template.md",
      "absolute_path": "/app/repo/Sample Pack Review Template.md",
      "categories": [
        {
          "category": "instruments",
          "score": 8.5
        },
        {
          "category": "production",
          "score": 7.5
        },
        {
          "category": "ml_ai",
          "score": 5.0
        },
        {
          "category": "daw_integration",
          "score": 4.5
        },
        {
          "category": "composition",
          "score": 3.5
        },
        {
          "category": "theory",
          "score": 2.0
        },
        {
          "category": "audio_processing",
          "score": 1.0
        }
      ],
      "pipelines": []
    },
    {
      "path": "Humanization Cheat Sheet.md",
      "absolute_path": "/app/repo/Humanization Cheat Sheet.md",
      "categories": [
        {
          "category": "instruments",
          "score": 9.5
        },
        {
          "category": "production",
          "score": 8.0
        },
        {
          "category": "theory",
          "score": 4.5
        },
        {
          "category": "daw_integration",
          "score": 3.5
        },
        {
          "category": "ml_ai",
          "score": 2.5
        },
        {
          "category": "audio_processing",
          "score": 2.5
        },
        {
          "category": "tools",
          "score": 1.0
        }
      ],
      "pipelines": []
    },
    {
      "path": "MVP_COMPLETE copy.md",
      "absolute_path": "/app/repo/MVP_COMPLETE copy.md",
      "categories": [
        {
          "category": "instruments",
          "score": 7.0
        },
        {
          "category": "production",
          "score": 6.5
        },
        {
          "category": "audio_processing",
          "score": 5.5
        },
        {
          "category": "tools",
          "score": 4.0
        },
        {
          "category": "daw_integration",
          "score": 3.5
        },
        {
          "category": "composition",
          "score": 3.5
        },
        {
          "category": "ml_ai",
          "score": 2.5
        },
        {
          "category": "emotion",
          "score": 2.5
        },
        {
          "category": "theory",
          "score": 2.0
        }
      ],
      "pipelines": []
    },
    {
      "path": "Python_Tools/utils/instruments.py",
      "absolute_path": "/app/repo/Python_Tools/utils/instruments.py",
      "categories": [
        {
          "category": "instruments",
          "score": 14.0
        },
        {
          "category": "theory",
          "score": 7.0
        },
        {
          "category": "tools",
          "score": 7.0
        },
        {
          "category": "production",
          "score": 2.5
        },
        {
          "category": "daw_integration",
          "score": 2.0
        },
        {
          "category": "audio_processing",
          "score": 1.0
        }
      ],
      "pipelines": []
    },
    {
      "path": "Python_Tools/utils/orchestral.py",
      "absolute_path": "/app/repo/Python_Tools/utils/orchestral.py",
      "categories": [
        {
          "category": "instruments",
          "score": 8.0
        },
        {
          "category": "tools",
          "score": 8.0
        },
        {
          "category": "ml_ai",
          "score": 2.5
        },
        {
          "category": "theory",
          "score": 1.0
        },
        {
          "category": "daw_integration",
          "score": 1.0
        }
      ],
      "pipelines": []
    },
    {
      "path": "Python_Tools/groove/groove_extractor.py",
      "absolute_path": "/app/repo/Python_Tools/groove/groove_extractor.py",
      "categories": [
        {
          "category": "instruments",
          "score": 12.0
        },
        {
          "category": "tools",
          "score": 7.0
        },
        {
          "category": "ml_ai",
          "score": 5.0
        },
        {
          "category": "production",
          "score": 3.5
        },
        {
          "category": "composition",
          "score": 3.5
        },
        {
          "category": "audio_processing",
          "score": 2.5
        },
        {
          "category": "daw_integration",
          "score": 2.0
        },
        {
          "category": "theory",
          "score": 1.0
        }
      ],
      "pipelines": []
    },
    {
      "path": "Production_Workflows/Synth_Humanization_Guide.md",
      "absolute_path": "/app/repo/Production_Workflows/Synth_Humanization_Guide.md",
      "categories": [
        {
          "category": "instruments",
          "score": 14.0
        },
        {
          "category": "production",
          "score": 10.5
        },
        {
          "category": "tools",
          "score": 6.0
        },
        {
          "category": "daw_integration",
          "score": 5.5
        },
        {
          "category": "ml_ai",
          "score": 5.0
        },
        {
          "category": "theory",
          "score": 4.5
        },
        {
          "category": "audio_processing",
          "score": 3.5
        },
        {
          "category": "composition",
          "score": 1.0
        }
      ],
      "pipelines": []
    },
    {
      "path": "python/penta_core/rules/timing.py",
      "absolute_path": "/app/repo/python/penta_core/rules/timing.py",
      "categories": [
        {
          "category": "instruments",
          "score": 4.5
        },
        {
          "category": "ml_ai",
          "score": 2.5
        },
        {
          "category": "daw_integration",
          "score": 1.0
        }
      ],
      "pipelines": [
        "standalone"
      ]
    },
    {
      "path": "python/penta_core/groove/drum_replacement.py",
      "absolute_path": "/app/repo/python/penta_core/groove/drum_replacement.py",
      "categories": [
        {
          "category": "instruments",
          "score": 8.0
        },
        {
          "category": "production",
          "score": 5.0
        },
        {
          "category": "ml_ai",
          "score": 2.5
        },
        {
          "category": "tools",
          "score": 2.5
        },
        {
          "category": "daw_integration",
          "score": 2.0
        },
        {
          "category": "theory",
          "score": 1.0
        },
        {
          "category": "audio_processing",
          "score": 1.0
        },
        {
          "category": "composition",
          "score": 1.0
        }
      ],
      "pipelines": [
        "shared"
      ]
    },
    {
      "path": "python/penta_core/groove/__init__.py",
      "absolute_path": "/app/repo/python/penta_core/groove/__init__.py",
      "categories": [
        {
          "category": "instruments",
          "score": 2.5
        },
        {
          "category": "theory",
          "score": 1.0
        }
      ],
      "pipelines": []
    },
    {
      "path": "docs_penta-core/instrument-learning-research.md",
      "absolute_path": "/app/repo/docs_penta-core/instrument-learning-research.md",
      "categories": [
        {
          "category": "instruments",
          "score": 11.5
        },
        {
          "category": "ml_ai",
          "score": 10.0
        },
        {
          "category": "theory",
          "score": 9.0
        },
        {
          "category": "tools",
          "score": 6.0
        },
        {
          "category": "production",
          "score": 3.5
        },
        {
          "category": "audio_processing",
          "score": 3.5
        },
        {
          "category": "daw_integration",
          "score": 3.5
        },
        {
          "category": "composition",
          "score": 2.0
        }
      ],
      "pipelines": []
    },
    {
      "path": "lost-and-found/archives-extracted/kelly-project-1/kelly/src/kelly/engines/fill_engine.py",
      "absolute_path": "/app/repo/lost-and-found/archives-extracted/kelly-project-1/kelly/src/kelly/engines/fill_engine.py",
      "categories": [
        {
          "category": "instruments",
          "score": 2.5
        },
        {
          "category": "emotion",
          "score": 2.5
        }
      ],
      "pipelines": [
        "daw"
      ]
    },
    {
      "path": "lost-and-found/archives-extracted/kelly-project-2/kelly/src/kelly/engines/fill_engine.py",
      "absolute_path": "/app/repo/lost-and-found/archives-extracted/kelly-project-2/kelly/src/kelly/engines/fill_engine.py",
      "categories": [
        {
          "category": "instruments",
          "score": 2.5
        },
        {
          "category": "emotion",
          "score": 2.5
        }
      ],
      "pipelines": [
        "daw"
      ]
    },
    {
      "path": "lost-and-found/archives-extracted/kelly-project-nested/kelly/src/kelly/engines/fill_engine.py",
      "absolute_path": "/app/repo/lost-and-found/archives-extracted/kelly-project-nested/kelly/src/kelly/engines/fill_engine.py",
      "categories": [
        {
          "category": "instruments",
          "score": 2.5
        },
        {
          "category": "emotion",
          "score": 2.5
        }
      ],
      "pipelines": [
        "daw"
      ]
    },
    {
      "path": "lost-and-found/onedrive-recovery/txt-files/MPK_Mini3_Knob_Assignments.txt",
      "absolute_path": "/app/repo/lost-and-found/onedrive-recovery/txt-files/MPK_Mini3_Knob_Assignments.txt",
      "categories": [
        {
          "category": "instruments",
          "score": 8.5
        },
        {
          "category": "production",
          "score": 5.5
        },
        {
          "category": "daw_integration",
          "score": 3.5
        },
        {
          "category": "ml_ai",
          "score": 2.5
        },
        {
          "category": "audio_processing",
          "score": 2.5
        },
        {
          "category": "theory",
          "score": 1.0
        }
      ],
      "pipelines": []
    },
    {
      "path": "lost-and-found/onedrive-recovery/txt-files/Logic_Template_Setup_Guide.txt",
      "absolute_path": "/app/repo/lost-and-found/onedrive-recovery/txt-files/Logic_Template_Setup_Guide.txt",
      "categories": [
        {
          "category": "instruments",
          "score": 9.5
        },
        {
          "category": "daw_integration",
          "score": 9.0
        },
        {
          "category": "theory",
          "score": 5.5
        },
        {
          "category": "production",
          "score": 4.5
        },
        {
          "category": "composition",
          "score": 3.5
        },
        {
          "category": "ml_ai",
          "score": 2.5
        },
        {
          "category": "audio_processing",
          "score": 1.0
        }
      ],
      "pipelines": []
    },
    {
      "path": "final kel/UPLOAD_BATCH_3.txt",
      "absolute_path": "/app/repo/final kel/UPLOAD_BATCH_3.txt",
      "categories": [
        {
          "category": "instruments",
          "score": 3.5
        },
        {
          "category": "theory",
          "score": 2.5
        },
        {
          "category": "emotion",
          "score": 2.5
        },
        {
          "category": "production",
          "score": 1.0
        }
      ],
      "pipelines": []
    },
    {
      "path": "final kel/UPLOAD_BATCH_5.txt",
      "absolute_path": "/app/repo/final kel/UPLOAD_BATCH_5.txt",
      "categories": [
        {
          "category": "instruments",
          "score": 5.0
        },
        {
          "category": "theory",
          "score": 3.5
        },
        {
          "category": "ml_ai",
          "score": 2.5
        },
        {
          "category": "audio_processing",
          "score": 2.5
        },
        {
          "category": "composition",
          "score": 2.5
        },
        {
          "category": "emotion",
          "score": 2.5
        },
        {
          "category": "daw_integration",
          "score": 1.0
        }
      ],
      "pipelines": []
    },
    {
      "path": "final kel/TXT/CMakeLists.txt",
      "absolute_path": "/app/repo/final kel/TXT/CMakeLists.txt",
      "categories": [
        {
          "category": "instruments",
          "score": 9.5
        },
        {
          "category": "emotion",
          "score": 7.0
        },
        {
          "category": "tools",
          "score": 6.5
        },
        {
          "category": "theory",
          "score": 6.0
        },
        {
          "category": "audio_processing",
          "score": 5.5
        },
        {
          "category": "production",
          "score": 3.5
        },
        {
          "category": "composition",
          "score": 3.5
        },
        {
          "category": "daw_integration",
          "score": 3.0
        },
        {
          "category": "ml_ai",
          "score": 2.5
        }
      ],
      "pipelines": []
    },
    {
      "path": "final kel/MARKDOWN/INTEGRATION_STATUS.md",
      "absolute_path": "/app/repo/final kel/MARKDOWN/INTEGRATION_STATUS.md",
      "categories": [
        {
          "category": "instruments",
          "score": 3.5
        },
        {
          "category": "production",
          "score": 2.5
        },
        {
          "category": "theory",
          "score": 2.5
        },
        {
          "category": "ml_ai",
          "score": 2.5
        },
        {
          "category": "emotion",
          "score": 2.5
        },
        {
          "category": "audio_processing",
          "score": 2.0
        },
        {
          "category": "daw_integration",
          "score": 2.0
        },
        {
          "category": "tools",
          "score": 1.0
        }
      ],
      "pipelines": []
    },
    {
      "path": "final kel/lost-and-found/music-project/Kelly_Song_Project/LYRICS_V4_MASTERS_SYNTHESIS.md",
      "absolute_path": "/app/repo/final kel/lost-and-found/music-project/Kelly_Song_Project/LYRICS_V4_MASTERS_SYNTHESIS.md",
      "categories": [
        {
          "category": "instruments",
          "score": 9.5
        },
        {
          "category": "composition",
          "score": 9.0
        },
        {
          "category": "production",
          "score": 7.5
        },
        {
          "category": "audio_processing",
          "score": 7.0
        },
        {
          "category": "emotion",
          "score": 5.0
        },
        {
          "category": "ml_ai",
          "score": 4.0
        },
        {
          "category": "theory",
          "score": 3.5
        },
        {
          "category": "daw_integration",
          "score": 1.0
        }
      ],
      "pipelines": []
    },
    {
      "path": "final kel/lost-and-found/python-packages/kelly 3/src/kelly/engines/fill_engine.py",
      "absolute_path": "/app/repo/final kel/lost-and-found/python-packages/kelly 3/src/kelly/engines/fill_engine.py",
      "categories": [
        {
          "category": "instruments",
          "score": 2.5
        },
        {
          "category": "emotion",
          "score": 2.5
        }
      ],
      "pipelines": []
    },
    {
      "path": "final kel/lost-and-found/python-packages/kelly 2/src/kelly/engines/fill_engine.py",
      "absolute_path": "/app/repo/final kel/lost-and-found/python-packages/kelly 2/src/kelly/engines/fill_engine.py",
      "categories": [
        {
          "category": "instruments",
          "score": 2.5
        },
        {
          "category": "emotion",
          "score": 2.5
        }
      ],
      "pipelines": []
    },
    {
      "path": "final kel/lost-and-found/python-packages/kelly/src/kelly/engines/fill_engine.py",
      "absolute_path": "/app/repo/final kel/lost-and-found/python-packages/kelly/src/kelly/engines/fill_engine.py",
      "categories": [
        {
          "category": "instruments",
          "score": 2.5
        },
        {
          "category": "emotion",
          "score": 2.5
        }
      ],
      "pipelines": []
    },
    {
      "path": "final kel/tests/midi/test_instrument_selector.cpp",
      "absolute_path": "/app/repo/final kel/tests/midi/test_instrument_selector.cpp",
      "categories": [
        {
          "category": "instruments",
          "score": 3.0
        },
        {
          "category": "emotion",
          "score": 2.5
        },
        {
          "category": "composition",
          "score": 2.0
        },
        {
          "category": "daw_integration",
          "score": 1.0
        }
      ],
      "pipelines": []
    },
    {
      "path": "final kel/tests/engines/test_rhythm_engine.cpp",
      "absolute_path": "/app/repo/final kel/tests/engines/test_rhythm_engine.cpp",
      "categories": [
        {
          "category": "instruments",
          "score": 3.5
        },
        {
          "category": "theory",
          "score": 3.0
        },
        {
          "category": "ml_ai",
          "score": 2.5
        },
        {
          "category": "emotion",
          "score": 2.5
        },
        {
          "category": "production",
          "score": 1.0
        },
        {
          "category": "daw_integration",
          "score": 1.0
        }
      ],
      "pipelines": [
        "standalone"
      ]
    },
    {
      "path": "final kel/data/genre_pocket_maps.json",
      "absolute_path": "/app/repo/final kel/data/genre_pocket_maps.json",
      "categories": [
        {
          "category": "instruments",
          "score": 6.0
        },
        {
          "category": "ml_ai",
          "score": 4.0
        },
        {
          "category": "tools",
          "score": 2.5
        },
        {
          "category": "daw_integration",
          "score": 2.0
        },
        {
          "category": "theory",
          "score": 1.0
        }
      ],
      "pipelines": []
    },
    {
      "path": "final kel/reference/python_kelly/engines/fill_engine.py",
      "absolute_path": "/app/repo/final kel/reference/python_kelly/engines/fill_engine.py",
      "categories": [
        {
          "category": "instruments",
          "score": 2.5
        },
        {
          "category": "emotion",
          "score": 2.5
        }
      ],
      "pipelines": []
    },
    {
      "path": "final kel/reference/daiw_music_brain/music_brain/utils/instruments.py",
      "absolute_path": "/app/repo/final kel/reference/daiw_music_brain/music_brain/utils/instruments.py",
      "categories": [
        {
          "category": "instruments",
          "score": 15.0
        },
        {
          "category": "ml_ai",
          "score": 7.0
        },
        {
          "category": "daw_integration",
          "score": 4.5
        },
        {
          "category": "production",
          "score": 4.0
        },
        {
          "category": "theory",
          "score": 2.5
        },
        {
          "category": "tools",
          "score": 2.5
        },
        {
          "category": "audio_processing",
          "score": 1.0
        },
        {
          "category": "composition",
          "score": 1.0
        }
      ],
      "pipelines": []
    },
    {
      "path": "final kel/reference/daiw_music_brain/vault/Production_Workflows/suno_omega_synthesis_v2.md",
      "absolute_path": "/app/repo/final kel/reference/daiw_music_brain/vault/Production_Workflows/suno_omega_synthesis_v2.md",
      "categories": [
        {
          "category": "instruments",
          "score": 14.0
        },
        {
          "category": "ml_ai",
          "score": 13.0
        },
        {
          "category": "production",
          "score": 11.0
        },
        {
          "category": "audio_processing",
          "score": 10.0
        },
        {
          "category": "emotion",
          "score": 7.0
        },
        {
          "category": "theory",
          "score": 5.5
        },
        {
          "category": "daw_integration",
          "score": 5.5
        },
        {
          "category": "composition",
          "score": 1.0
        }
      ],
      "pipelines": []
    },
    {
      "path": "final kel/src/ui/PianoRollPreview.h",
      "absolute_path": "/app/repo/final kel/src/ui/PianoRollPreview.h",
      "categories": [
        {
          "category": "instruments",
          "score": 7.0
        },
        {
          "category": "ml_ai",
          "score": 2.5
        },
        {
          "category": "daw_integration",
          "score": 1.0
        }
      ],
      "pipelines": []
    },
    {
      "path": "final kel/src/ui/PianoRollPreview.cpp",
      "absolute_path": "/app/repo/final kel/src/ui/PianoRollPreview.cpp",
      "categories": [
        {
          "category": "instruments",
          "score": 8.0
        },
        {
          "category": "theory",
          "score": 5.0
        },
        {
          "category": "ml_ai",
          "score": 2.5
        },
        {
          "category": "daw_integration",
          "score": 1.0
        }
      ],
      "pipelines": []
    },
    {
      "path": "final kel/src/midi/InstrumentSelector.cpp",
      "absolute_path": "/app/repo/final kel/src/midi/InstrumentSelector.cpp",
      "categories": [
        {
          "category": "instruments",
          "score": 15.0
        },
        {
          "category": "theory",
          "score": 5.0
        },
        {
          "category": "emotion",
          "score": 5.0
        },
        {
          "category": "production",
          "score": 4.0
        },
        {
          "category": "composition",
          "score": 3.5
        },
        {
          "category": "ml_ai",
          "score": 2.5
        },
        {
          "category": "audio_processing",
          "score": 1.0
        },
        {
          "category": "daw_integration",
          "score": 1.0
        }
      ],
      "pipelines": [
        "standalone"
      ]
    },
    {
      "path": "final kel/src/midi/InstrumentSelector.h",
      "absolute_path": "/app/repo/final kel/src/midi/InstrumentSelector.h",
      "categories": [
        {
          "category": "instruments",
          "score": 15.0
        },
        {
          "category": "emotion",
          "score": 6.0
        },
        {
          "category": "theory",
          "score": 5.0
        },
        {
          "category": "production",
          "score": 4.0
        },
        {
          "category": "ml_ai",
          "score": 2.5
        },
        {
          "category": "daw_integration",
          "score": 2.0
        },
        {
          "category": "audio_processing",
          "score": 1.0
        },
        {
          "category": "composition",
          "score": 1.0
        }
      ],
      "pipelines": []
    },
    {
      "path": "final kel/src/plugin/PluginEditor.cpp",
      "absolute_path": "/app/repo/final kel/src/plugin/PluginEditor.cpp",
      "categories": [
        {
          "category": "instruments",
          "score": 9.5
        },
        {
          "category": "theory",
          "score": 7.0
        },
        {
          "category": "daw_integration",
          "score": 6.5
        },
        {
          "category": "emotion",
          "score": 6.0
        },
        {
          "category": "production",
          "score": 4.5
        },
        {
          "category": "ml_ai",
          "score": 4.0
        },
        {
          "category": "tools",
          "score": 3.5
        },
        {
          "category": "audio_processing",
          "score": 2.0
        }
      ],
      "pipelines": [
        "plugin"
      ]
    },
    {
      "path": "final kel/src/voice/VoiceSynthesizer.h",
      "absolute_path": "/app/repo/final kel/src/voice/VoiceSynthesizer.h",
      "categories": [
        {
          "category": "instruments",
          "score": 7.0
        },
        {
          "category": "production",
          "score": 3.5
        },
        {
          "category": "audio_processing",
          "score": 3.5
        },
        {
          "category": "theory",
          "score": 2.5
        },
        {
          "category": "emotion",
          "score": 2.5
        },
        {
          "category": "tools",
          "score": 2.5
        },
        {
          "category": "daw_integration",
          "score": 1.0
        },
        {
          "category": "composition",
          "score": 1.0
        }
      ],
      "pipelines": []
    },
    {
      "path": "final kel/src/voice/LyriSync.cpp",
      "absolute_path": "/app/repo/final kel/src/voice/LyriSync.cpp",
      "categories": [
        {
          "category": "instruments",
          "score": 2.5
        },
        {
          "category": "daw_integration",
          "score": 1.0
        },
        {
          "category": "composition",
          "score": 1.0
        }
      ],
      "pipelines": []
    },
    {
      "path": "final kel/src/engines/DrumGrooveEngine.cpp",
      "absolute_path": "/app/repo/final kel/src/engines/DrumGrooveEngine.cpp",
      "categories": [
        {
          "category": "instruments",
          "score": 7.0
        },
        {
          "category": "ml_ai",
          "score": 2.5
        },
        {
          "category": "emotion",
          "score": 2.5
        },
        {
          "category": "daw_integration",
          "score": 1.0
        }
      ],
      "pipelines": []
    },
    {
      "path": "final kel/src/engines/ArrangementEngine.cpp",
      "absolute_path": "/app/repo/final kel/src/engines/ArrangementEngine.cpp",
      "categories": [
        {
          "category": "instruments",
          "score": 12.0
        },
        {
          "category": "composition",
          "score": 10.0
        },
        {
          "category": "theory",
          "score": 3.5
        },
        {
          "category": "emotion",
          "score": 2.5
        },
        {
          "category": "daw_integration",
          "score": 1.0
        }
      ],
      "pipelines": [
        "daw"
      ]
    },
    {
      "path": "final kel/src/engines/DrumGrooveEngine.h",
      "absolute_path": "/app/repo/final kel/src/engines/DrumGrooveEngine.h",
      "categories": [
        {
          "category": "instruments",
          "score": 7.0
        },
        {
          "category": "ml_ai",
          "score": 2.5
        },
        {
          "category": "emotion",
          "score": 2.5
        }
      ],
      "pipelines": []
    },
    {
      "path": "docs/instrument-learning-research.md",
      "absolute_path": "/app/repo/docs/instrument-learning-research.md",
      "categories": [
        {
          "category": "instruments",
          "score": 11.5
        },
        {
          "category": "ml_ai",
          "score": 10.0
        },
        {
          "category": "theory",
          "score": 9.0
        },
        {
          "category": "tools",
          "score": 6.0
        },
        {
          "category": "production",
          "score": 3.5
        },
        {
          "category": "audio_processing",
          "score": 3.5
        },
        {
          "category": "daw_integration",
          "score": 3.5
        },
        {
          "category": "composition",
          "score": 2.0
        }
      ],
      "pipelines": []
    },
    {
      "path": "iDAW_Core/data/LearningInstruments.json",
      "absolute_path": "/app/repo/iDAW_Core/data/LearningInstruments.json",
      "categories": [
        {
          "category": "instruments",
          "score": 15.0
        },
        {
          "category": "production",
          "score": 9.5
        },
        {
          "category": "theory",
          "score": 9.5
        },
        {
          "category": "daw_integration",
          "score": 8.0
        },
        {
          "category": "audio_processing",
          "score": 7.0
        },
        {
          "category": "composition",
          "score": 7.0
        },
        {
          "category": "ml_ai",
          "score": 5.0
        },
        {
          "category": "tools",
          "score": 2.5
        }
      ],
      "pipelines": []
    },
    {
      "path": "iDAW_Core/data/LearningSources.json",
      "absolute_path": "/app/repo/iDAW_Core/data/LearningSources.json",
      "categories": [
        {
          "category": "instruments",
          "score": 13.0
        },
        {
          "category": "production",
          "score": 11.0
        },
        {
          "category": "daw_integration",
          "score": 9.0
        },
        {
          "category": "ml_ai",
          "score": 7.5
        },
        {
          "category": "tools",
          "score": 5.0
        },
        {
          "category": "theory",
          "score": 4.5
        },
        {
          "category": "composition",
          "score": 3.5
        },
        {
          "category": "audio_processing",
          "score": 1.0
        }
      ],
      "pipelines": []
    },
    {
      "path": "Data_Files/genre_pocket_maps.json",
      "absolute_path": "/app/repo/Data_Files/genre_pocket_maps.json",
      "categories": [
        {
          "category": "instruments",
          "score": 6.0
        },
        {
          "category": "ml_ai",
          "score": 4.0
        },
        {
          "category": "tools",
          "score": 2.5
        },
        {
          "category": "daw_integration",
          "score": 2.0
        },
        {
          "category": "theory",
          "score": 1.0
        }
      ],
      "pipelines": []
    },
    {
      "path": "Obsidian_Documentation/Sample_Library_Index.md",
      "absolute_path": "/app/repo/Obsidian_Documentation/Sample_Library_Index.md",
      "categories": [
        {
          "category": "instruments",
          "score": 8.5
        },
        {
          "category": "production",
          "score": 3.5
        },
        {
          "category": "daw_integration",
          "score": 3.5
        },
        {
          "category": "composition",
          "score": 3.5
        },
        {
          "category": "ml_ai",
          "score": 2.5
        },
        {
          "category": "tools",
          "score": 2.5
        },
        {
          "category": "theory",
          "score": 1.0
        },
        {
          "category": "audio_processing",
          "score": 1.0
        }
      ],
      "pipelines": []
    },
    {
      "path": "music_brain/learning/instruments.py",
      "absolute_path": "/app/repo/music_brain/learning/instruments.py",
      "categories": [
        {
          "category": "instruments",
          "score": 15.0
        },
        {
          "category": "theory",
          "score": 10.5
        },
        {
          "category": "production",
          "score": 9.5
        },
        {
          "category": "ml_ai",
          "score": 9.5
        },
        {
          "category": "composition",
          "score": 8.0
        },
        {
          "category": "audio_processing",
          "score": 7.0
        },
        {
          "category": "daw_integration",
          "score": 3.5
        }
      ],
      "pipelines": [
        "daw"
      ]
    },
    {
      "path": "music_brain/learning/resources.py",
      "absolute_path": "/app/repo/music_brain/learning/resources.py",
      "categories": [
        {
          "category": "instruments",
          "score": 13.0
        },
        {
          "category": "production",
          "score": 12.0
        },
        {
          "category": "ml_ai",
          "score": 12.0
        },
        {
          "category": "theory",
          "score": 8.0
        },
        {
          "category": "tools",
          "score": 5.0
        },
        {
          "category": "daw_integration",
          "score": 4.5
        },
        {
          "category": "composition",
          "score": 4.5
        },
        {
          "category": "audio_processing",
          "score": 3.5
        }
      ],
      "pipelines": [
        "daw"
      ]
    },
    {
      "path": "music_brain/utils/instruments.py",
      "absolute_path": "/app/repo/music_brain/utils/instruments.py",
      "categories": [
        {
          "category": "instruments",
          "score": 15.0
        },
        {
          "category": "ml_ai",
          "score": 7.0
        },
        {
          "category": "daw_integration",
          "score": 4.5
        },
        {
          "category": "production",
          "score": 4.0
        },
        {
          "category": "theory",
          "score": 2.5
        },
        {
          "category": "tools",
          "score": 2.5
        },
        {
          "category": "audio_processing",
          "score": 1.0
        },
        {
          "category": "composition",
          "score": 1.0
        }
      ],
      "pipelines": []
    },
    {
      "path": "music_brain/daw/pro_tools.py",
      "absolute_path": "/app/repo/music_brain/daw/pro_tools.py",
      "categories": [
        {
          "category": "instruments",
          "score": 12.0
        },
        {
          "category": "daw_integration",
          "score": 10.0
        },
        {
          "category": "production",
          "score": 9.5
        },
        {
          "category": "tools",
          "score": 9.5
        },
        {
          "category": "ml_ai",
          "score": 7.0
        },
        {
          "category": "audio_processing",
          "score": 4.5
        },
        {
          "category": "theory",
          "score": 1.0
        },
        {
          "category": "composition",
          "score": 1.0
        }
      ],
      "pipelines": [
        "daw"
      ]
    },
    {
      "path": "Templates/Sample_Pack_Review_Template.md",
      "absolute_path": "/app/repo/Templates/Sample_Pack_Review_Template.md",
      "categories": [
        {
          "category": "instruments",
          "score": 8.5
        },
        {
          "category": "production",
          "score": 7.5
        },
        {
          "category": "ml_ai",
          "score": 5.0
        },
        {
          "category": "daw_integration",
          "score": 4.5
        },
        {
          "category": "composition",
          "score": 3.5
        },
        {
          "category": "theory",
          "score": 2.0
        },
        {
          "category": "audio_processing",
          "score": 1.0
        }
      ],
      "pipelines": []
    },
    {
      "path": "external/JUCE/examples/Plugins/AUv3SynthPluginDemo.h",
      "absolute_path": "/app/repo/external/JUCE/examples/Plugins/AUv3SynthPluginDemo.h",
      "categories": [
        {
          "category": "instruments",
          "score": 9.5
        },
        {
          "category": "production",
          "score": 8.5
        },
        {
          "category": "daw_integration",
          "score": 6.0
        },
        {
          "category": "ml_ai",
          "score": 5.0
        },
        {
          "category": "audio_processing",
          "score": 4.5
        },
        {
          "category": "tools",
          "score": 4.0
        },
        {
          "category": "composition",
          "score": 1.0
        }
      ],
      "pipelines": [
        "plugin"
      ]
    },
    {
      "path": "external/JUCE/modules/juce_audio_basics/midi/juce_MidiMessage.cpp",
      "absolute_path": "/app/repo/external/JUCE/modules/juce_audio_basics/midi/juce_MidiMessage.cpp",
      "categories": [
        {
          "category": "instruments",
          "score": 13.0
        },
        {
          "category": "production",
          "score": 12.0
        },
        {
          "category": "theory",
          "score": 8.0
        },
        {
          "category": "audio_processing",
          "score": 5.5
        },
        {
          "category": "composition",
          "score": 4.5
        },
        {
          "category": "daw_integration",
          "score": 4.0
        },
        {
          "category": "tools",
          "score": 3.5
        },
        {
          "category": "ml_ai",
          "score": 2.5
        }
      ],
      "pipelines": [
        "plugin"
      ]
    },
    {
      "path": "vault/Production_Guides/Groove and Rhythm Guide.md",
      "absolute_path": "/app/repo/vault/Production_Guides/Groove and Rhythm Guide.md",
      "categories": [
        {
          "category": "instruments",
          "score": 12.0
        },
        {
          "category": "daw_integration",
          "score": 5.5
        },
        {
          "category": "theory",
          "score": 4.0
        },
        {
          "category": "production",
          "score": 2.5
        },
        {
          "category": "ml_ai",
          "score": 2.5
        },
        {
          "category": "emotion",
          "score": 2.5
        },
        {
          "category": "tools",
          "score": 2.5
        }
      ],
      "pipelines": []
    },
    {
      "path": "vault/Production_Guides/Bass Programming Guide.md",
      "absolute_path": "/app/repo/vault/Production_Guides/Bass Programming Guide.md",
      "categories": [
        {
          "category": "instruments",
          "score": 11.5
        },
        {
          "category": "production",
          "score": 7.0
        },
        {
          "category": "daw_integration",
          "score": 6.5
        },
        {
          "category": "theory",
          "score": 4.5
        },
        {
          "category": "audio_processing",
          "score": 3.5
        },
        {
          "category": "tools",
          "score": 3.5
        },
        {
          "category": "ml_ai",
          "score": 2.5
        }
      ],
      "pipelines": []
    },
    {
      "path": "vault/Production_Guides/Dynamics and Arrangement Guide.md",
      "absolute_path": "/app/repo/vault/Production_Guides/Dynamics and Arrangement Guide.md",
      "categories": [
        {
          "category": "instruments",
          "score": 12.0
        },
        {
          "category": "composition",
          "score": 11.5
        },
        {
          "category": "theory",
          "score": 10.5
        },
        {
          "category": "production",
          "score": 9.5
        },
        {
          "category": "ml_ai",
          "score": 4.0
        },
        {
          "category": "audio_processing",
          "score": 3.5
        },
        {
          "category": "tools",
          "score": 3.5
        },
        {
          "category": "daw_integration",
          "score": 3.0
        },
        {
          "category": "emotion",
          "score": 2.5
        }
      ],
      "pipelines": []
    },
    {
      "path": "vault/Production_Guides/Guitar Programming Guide.md",
      "absolute_path": "/app/repo/vault/Production_Guides/Guitar Programming Guide.md",
      "categories": [
        {
          "category": "instruments",
          "score": 10.5
        },
        {
          "category": "theory",
          "score": 9.5
        },
        {
          "category": "production",
          "score": 8.5
        },
        {
          "category": "daw_integration",
          "score": 4.5
        },
        {
          "category": "ml_ai",
          "score": 2.5
        },
        {
          "category": "composition",
          "score": 2.0
        }
      ],
      "pipelines": []
    }
  ],
  "file_count": 73
}